entung_tea/__init__.py
entung_tea-0.1.1.dist-info/METADATA
entung_tea-0.1.1.dist-info/WHEEL
entung_tea-0.1.1.dist-info/top_level.txt
entung_tea-0.1.1.dist-info/RECORD
